geocoding/__init__.py
geocoding/main.py
geocoding_cli-1.0.3.dist-info/licenses/LICENSE
geocoding_cli-1.0.3.dist-info/METADATA
geocoding_cli-1.0.3.dist-info/WHEEL
geocoding_cli-1.0.3.dist-info/entry_points.txt
geocoding_cli-1.0.3.dist-info/top_level.txt
geocoding_cli-1.0.3.dist-info/RECORD
