Metadata-Version: 2.4
Name: geocoding-cli
Version: 1.0.3
Summary: 将 Excel 中的地址列批量转换为经纬度（百度地图 API）
Home-page: https://github.com/zzhoo8/geocoding-cli
Author: zzhoo8
Author-email: zzhoo8@gmail.com
License: LicenseRef-Proprietary
Keywords: geocoding
Classifier: Programming Language :: Python :: 3.10
Classifier: License :: OSI Approved :: MIT License
Classifier: Operating System :: OS Independent
Requires-Python: >=3.10
License-File: LICENSE
Requires-Dist: openpyxl==3.1.5
Requires-Dist: requests==2.32.5
Requires-Dist: tqdm==4.67.1
Dynamic: author
Dynamic: author-email
Dynamic: classifier
Dynamic: description
Dynamic: description-content-type
Dynamic: home-page
Dynamic: keywords
Dynamic: license
Dynamic: license-file
Dynamic: requires-dist
Dynamic: requires-python
Dynamic: summary
